[{"nombre":"Dada Honey","id":1,"detalle":"dulce","precio":"1500","codigo":"DADA","stock":"10","thumbnail":"desafio-3/imagenes/cosecha.webp"},{"nombre":"Salentein Espumante Doux","id":2,"detalle":"Espumante","precio":3300,"codigo":"SALEN","stock":10,"thumbnail":["https://vinologos.com/wp-content/uploads/2023/04/Salentein-Doux.webp"],"status":true},{"nombre":"Jagermeister","id":3,"detalle":"herval","precio":"10000","codigo":"JAGER","stock":"10","thumbnail":"./desafio-3/imagenes/jager.jpg"},{"nombre":"Bombay Sapphire London Dry","id":4,"detalle":"blanca","precio":"7500","codigo":"BOMBAY","stock":"10","thumbnail":"https://http2.mlstatic.com/D_NQ_NP_2X_669612-MLA43643320606_102020-F.webp"},{"nombre":"Tequila Jose Cuervo Especial gold","id":5,"detalle":"blanca","precio":"10000","codigo":"GOLD","stock":"10","thumbnail":"./desafio-3/imagenes/cuervo-dorado.jpg"},{"nombre":"Tequila Jose Cuervo Especial silver","id":6,"detalle":"blanca","precio":"9000","codigo":"SILVER","stock":"10","thumbnail":"./desafio-3/imagenes/cuervo-plata.jpg"},{"nombre":"Chivas Mizunara","id":7,"detalle":"blanca","precio":"20500","codigo":"CHIVAS","stock":"10","thumbnail":"./desafio-3/imagenes/chivas.webp"},{"nombre":"Ron Medellín","id":8,"detalle":"blanca","precio":"40000","codigo":"MEDELLIN","stock":"10","thumbnail":"./desafio-3/imagenes/ron.jpg"},{"nombre":"Licor Frances De Violetas J. Cartron","id":9,"detalle":"dulce","precio":"10000","codigo":"VIO","stock":"10","thumbnail":"./desafio-3/imagenes/dulce1.webp"},{"nombre":"Emilia Dulce","id":10,"detalle":"dulce","precio":"1300","codigo":"EMILIA","stock":"10","thumbnail":"./desafio-3/imagenes/dulce2.webp"},{"id":11,"nombre":"Finca Las Moras","detalle":"Espumante Dadá 7 Sweet Pink","precio":2000,"thumbnail":["https://www.vinosyspirits.com/media/catalog/product/d/a/dada_7_sweet_pink.png?optimize=low&bg-color=255,255,255&fit=bounds&height=&width=&canvas=:"],"codigo":"PINK","stock":10,"status":false}]